[{"end_name":"jp.co.flect.excel2canvas.validator","relation_type":1,"start_name":"jp.co.flect.excel2canvas.validator.InputRuleTest"},{"end_name":"jp.co.flect.excel2canvas","relation_type":1,"start_name":"jp.co.flect.excel2canvas.InvoiceTest"},{"end_name":"jp.co.flect.excel2canvas","relation_type":1,"start_name":"jp.co.flect.excel2canvas.InvisibleTest"},{"end_name":"jp.co.flect.excel2canvas","relation_type":1,"start_name":"jp.co.flect.excel2canvas.JsonTest"},{"end_name":"jp.co.flect.excel2canvas","relation_type":1,"start_name":"jp.co.flect.excel2canvas.ChartTest"},{"end_name":"jp.co.flect.excel2canvas","relation_type":1,"start_name":"jp.co.flect.excel2canvas.ExcelToCanvasBuilder"},{"end_name":"jp.co.flect.excel2canvas","relation_type":1,"start_name":"jp.co.flect.excel2canvas.ExcelToCanvasBuilder.CellWrapper"},{"end_name":"jp.co.flect.excel2canvas","relation_type":1,"start_name":"jp.co.flect.excel2canvas.ExcelToCanvasBuilder.ExpandChecker"},{"end_name":"jp.co.flect.excel2canvas","relation_type":1,"start_name":"jp.co.flect.excel2canvas.ExcelToCanvasBuilder.BorderInfo"},{"end_name":"jp.co.flect.excel2canvas","relation_type":1,"start_name":"jp.co.flect.excel2canvas.FontManager"},{"end_name":"jp.co.flect.excel2canvas","relation_type":1,"start_name":"jp.co.flect.excel2canvas.NamedValueExtractor"},{"end_name":"jp.co.flect.excel2canvas","relation_type":1,"start_name":"jp.co.flect.excel2canvas.ExcelToCanvasMap"},{"end_name":"jp.co.flect.excel2canvas.validator","relation_type":1,"start_name":"jp.co.flect.excel2canvas.validator.InputRule"},{"end_name":"jp.co.flect.excel2canvas.validator","relation_type":1,"start_name":"jp.co.flect.excel2canvas.validator.InputRule.Validator"},{"end_name":"jp.co.flect.excel2canvas.validator","relation_type":1,"start_name":"jp.co.flect.excel2canvas.validator.InputRule.StringValidator"},{"end_name":"jp.co.flect.excel2canvas.validator.InputRule.Validator","relation_type":3,"start_name":"jp.co.flect.excel2canvas.validator.InputRule.StringValidator"},{"end_name":"jp.co.flect.excel2canvas.validator","relation_type":1,"start_name":"jp.co.flect.excel2canvas.validator.InputRule.IntegerValidator"},{"end_name":"jp.co.flect.excel2canvas.validator.InputRule.Validator","relation_type":3,"start_name":"jp.co.flect.excel2canvas.validator.InputRule.IntegerValidator"},{"end_name":"jp.co.flect.excel2canvas.validator","relation_type":1,"start_name":"jp.co.flect.excel2canvas.validator.InputRule.DecimalValidator"},{"end_name":"jp.co.flect.excel2canvas.validator.InputRule.Validator","relation_type":3,"start_name":"jp.co.flect.excel2canvas.validator.InputRule.DecimalValidator"},{"end_name":"jp.co.flect.excel2canvas.validator","relation_type":1,"start_name":"jp.co.flect.excel2canvas.validator.InputRule.ListValidator"},{"end_name":"jp.co.flect.excel2canvas.validator.InputRule.Validator","relation_type":3,"start_name":"jp.co.flect.excel2canvas.validator.InputRule.ListValidator"},{"end_name":"jp.co.flect.excel2canvas.validator","relation_type":1,"start_name":"jp.co.flect.excel2canvas.validator.InputRule.DateValidator"},{"end_name":"jp.co.flect.excel2canvas.validator.InputRule.Validator","relation_type":3,"start_name":"jp.co.flect.excel2canvas.validator.InputRule.DateValidator"},{"end_name":"jp.co.flect.excel2canvas.validator","relation_type":1,"start_name":"jp.co.flect.excel2canvas.validator.InputRule.TimeValidator"},{"end_name":"jp.co.flect.excel2canvas.validator.InputRule.Validator","relation_type":3,"start_name":"jp.co.flect.excel2canvas.validator.InputRule.TimeValidator"},{"end_name":"jp.co.flect.excel2canvas.validator","relation_type":1,"start_name":"jp.co.flect.excel2canvas.validator.InputRule.TextLengthValidator"},{"end_name":"jp.co.flect.excel2canvas.validator.InputRule.Validator","relation_type":3,"start_name":"jp.co.flect.excel2canvas.validator.InputRule.TextLengthValidator"},{"end_name":"jp.co.flect.excel2canvas.validator","relation_type":1,"start_name":"jp.co.flect.excel2canvas.validator.InputRule.FormulaValidator"},{"end_name":"jp.co.flect.excel2canvas.validator.InputRule.Validator","relation_type":3,"start_name":"jp.co.flect.excel2canvas.validator.InputRule.FormulaValidator"},{"end_name":"jp.co.flect.excel2canvas.validator","relation_type":1,"start_name":"jp.co.flect.excel2canvas.validator.InputRule.InvalidValueException"},{"end_name":"java.lang.Exception","relation_type":2,"start_name":"jp.co.flect.excel2canvas.validator.InputRule.InvalidValueException"},{"end_name":"jp.co.flect.excel2canvas.validator","relation_type":1,"start_name":"jp.co.flect.excel2canvas.validator.InputRule.EmptyValueException"},{"end_name":"java.lang.Exception","relation_type":2,"start_name":"jp.co.flect.excel2canvas.validator.InputRule.EmptyValueException"},{"end_name":"jp.co.flect.excel2canvas.validator","relation_type":1,"start_name":"jp.co.flect.excel2canvas.validator.ExtDataValidationExtractor"},{"end_name":"jp.co.flect.excel2canvas","relation_type":1,"start_name":"jp.co.flect.excel2canvas.ColumnWidth"},{"end_name":"jp.co.flect.excel2canvas.chart","relation_type":1,"start_name":"jp.co.flect.excel2canvas.chart.ChartFactory"},{"end_name":"jp.co.flect.excel2canvas.chart","relation_type":1,"start_name":"jp.co.flect.excel2canvas.chart.Flotr2"},{"end_name":"java.lang.Cloneable","relation_type":3,"start_name":"jp.co.flect.excel2canvas.chart.Flotr2"},{"end_name":"jp.co.flect.excel2canvas.chart","relation_type":1,"start_name":"jp.co.flect.excel2canvas.chart.Flotr2.Option"},{"end_name":"jp.co.flect.excel2canvas.chart","relation_type":1,"start_name":"jp.co.flect.excel2canvas.chart.Flotr2.Axis"},{"end_name":"jp.co.flect.excel2canvas.chart","relation_type":1,"start_name":"jp.co.flect.excel2canvas.chart.Flotr2.Grid"},{"end_name":"jp.co.flect.excel2canvas.chart","relation_type":1,"start_name":"jp.co.flect.excel2canvas.chart.Flotr2.Mouse"},{"end_name":"jp.co.flect.excel2canvas.chart","relation_type":1,"start_name":"jp.co.flect.excel2canvas.chart.Flotr2.Legend"},{"end_name":"jp.co.flect.excel2canvas.chart","relation_type":1,"start_name":"jp.co.flect.excel2canvas.chart.Flotr2.PieOption"},{"end_name":"jp.co.flect.excel2canvas.chart","relation_type":1,"start_name":"jp.co.flect.excel2canvas.chart.Flotr2.PieData"},{"end_name":"jp.co.flect.excel2canvas.chart","relation_type":1,"start_name":"jp.co.flect.excel2canvas.chart.Flotr2.BarOption"},{"end_name":"jp.co.flect.excel2canvas.chart","relation_type":1,"start_name":"jp.co.flect.excel2canvas.chart.Flotr2.SeriesData"},{"end_name":"jp.co.flect.excel2canvas.chart","relation_type":1,"start_name":"jp.co.flect.excel2canvas.chart.Flotr2.LineOption"},{"end_name":"jp.co.flect.excel2canvas.chart","relation_type":1,"start_name":"jp.co.flect.excel2canvas.chart.Flotr2.RadarOption"},{"end_name":"jp.co.flect.excel2canvas.chart","relation_type":1,"start_name":"jp.co.flect.excel2canvas.chart.Flotr2.BubbleOption"},{"end_name":"jp.co.flect.excel2canvas.chart","relation_type":1,"start_name":"jp.co.flect.excel2canvas.chart.Flotr2.BubbleData"},{"end_name":"jp.co.flect.excel2canvas.chart.Flotr2.SeriesData","relation_type":2,"start_name":"jp.co.flect.excel2canvas.chart.Flotr2.BubbleData"},{"end_name":"jp.co.flect.excel2canvas.chart","relation_type":1,"start_name":"jp.co.flect.excel2canvas.chart.Flotr2.NameInfo"},{"end_name":"jp.co.flect.excel2canvas.chart","relation_type":1,"start_name":"jp.co.flect.excel2canvas.chart.Flotr2.ValueInfo"},{"end_name":"jp.co.flect.excel2canvas.chart","relation_type":1,"start_name":"jp.co.flect.excel2canvas.chart.Flotr2ChartFactory"},{"end_name":"jp.co.flect.excel2canvas.chart","relation_type":1,"start_name":"jp.co.flect.excel2canvas.chart.Flotr2ChartFactory.SeriesWrapper"},{"end_name":"jp.co.flect.excel2canvas.chart","relation_type":1,"start_name":"jp.co.flect.excel2canvas.chart.Flotr2ChartFactory.PieSeries"},{"end_name":"jp.co.flect.excel2canvas.chart.Flotr2ChartFactory.SeriesWrapper","relation_type":2,"start_name":"jp.co.flect.excel2canvas.chart.Flotr2ChartFactory.PieSeries"},{"end_name":"jp.co.flect.excel2canvas.chart","relation_type":1,"start_name":"jp.co.flect.excel2canvas.chart.Flotr2ChartFactory.BarSeries"},{"end_name":"jp.co.flect.excel2canvas.chart.Flotr2ChartFactory.SeriesWrapper","relation_type":2,"start_name":"jp.co.flect.excel2canvas.chart.Flotr2ChartFactory.BarSeries"},{"end_name":"jp.co.flect.excel2canvas.chart","relation_type":1,"start_name":"jp.co.flect.excel2canvas.chart.Flotr2ChartFactory.LineSeries"},{"end_name":"jp.co.flect.excel2canvas.chart.Flotr2ChartFactory.SeriesWrapper","relation_type":2,"start_name":"jp.co.flect.excel2canvas.chart.Flotr2ChartFactory.LineSeries"},{"end_name":"jp.co.flect.excel2canvas.chart","relation_type":1,"start_name":"jp.co.flect.excel2canvas.chart.Flotr2ChartFactory.RadarSeries"},{"end_name":"jp.co.flect.excel2canvas.chart.Flotr2ChartFactory.SeriesWrapper","relation_type":2,"start_name":"jp.co.flect.excel2canvas.chart.Flotr2ChartFactory.RadarSeries"},{"end_name":"jp.co.flect.excel2canvas.chart","relation_type":1,"start_name":"jp.co.flect.excel2canvas.chart.Flotr2ChartFactory.BubbleSeries"},{"end_name":"jp.co.flect.excel2canvas.chart.Flotr2ChartFactory.SeriesWrapper","relation_type":2,"start_name":"jp.co.flect.excel2canvas.chart.Flotr2ChartFactory.BubbleSeries"},{"end_name":"jp.co.flect.excel2canvas.chart","relation_type":1,"start_name":"jp.co.flect.excel2canvas.chart.Chart"},{"end_name":"jp.co.flect.excel2canvas","relation_type":1,"start_name":"jp.co.flect.excel2canvas.ExcelUtils"},{"end_name":"jp.co.flect.excel2canvas","relation_type":1,"start_name":"jp.co.flect.excel2canvas.ExcelUtils.TempName"},{"end_name":"jp.co.flect.excel2canvas","relation_type":1,"start_name":"jp.co.flect.excel2canvas.ExcelToCanvas"},{"end_name":"jp.co.flect.excel2canvas","relation_type":1,"start_name":"jp.co.flect.excel2canvas.ExcelToCanvas.LineInfo"},{"end_name":"jp.co.flect.excel2canvas","relation_type":1,"start_name":"jp.co.flect.excel2canvas.ExcelToCanvas.FillInfo"},{"end_name":"jp.co.flect.excel2canvas","relation_type":1,"start_name":"jp.co.flect.excel2canvas.ExcelToCanvas.StrInfo"},{"end_name":"jp.co.flect.excel2canvas","relation_type":1,"start_name":"jp.co.flect.excel2canvas.ExcelToCanvas.PictureInfo"},{"end_name":"jp.co.flect.excel2canvas","relation_type":1,"start_name":"jp.co.flect.excel2canvas.ExcelToCanvas.ChartInfo"},{"end_name":"jp.co.flect.excel2canvas.format","relation_type":1,"start_name":"jp.co.flect.excel2canvas.format.ExcelDateFormat"},{"end_name":"java.text.Format","relation_type":2,"start_name":"jp.co.flect.excel2canvas.format.ExcelDateFormat"},{"end_name":"jp.co.flect.excel2canvas.format","relation_type":1,"start_name":"jp.co.flect.excel2canvas.format.ExcelDateFormat.Builder"},{"end_name":"jp.co.flect.excel2canvas.format","relation_type":1,"start_name":"jp.co.flect.excel2canvas.format.ExcelDateFormat.Const"},{"end_name":"jp.co.flect.excel2canvas.format.ExcelDateFormat.Builder","relation_type":3,"start_name":"jp.co.flect.excel2canvas.format.ExcelDateFormat.Const"},{"end_name":"jp.co.flect.excel2canvas.format","relation_type":1,"start_name":"jp.co.flect.excel2canvas.format.ExcelDateFormat.Year"},{"end_name":"jp.co.flect.excel2canvas.format.ExcelDateFormat.Builder","relation_type":3,"start_name":"jp.co.flect.excel2canvas.format.ExcelDateFormat.Year"},{"end_name":"jp.co.flect.excel2canvas.format","relation_type":1,"start_name":"jp.co.flect.excel2canvas.format.ExcelDateFormat.GregorianEra"},{"end_name":"jp.co.flect.excel2canvas.format.ExcelDateFormat.Builder","relation_type":3,"start_name":"jp.co.flect.excel2canvas.format.ExcelDateFormat.GregorianEra"},{"end_name":"jp.co.flect.excel2canvas.format","relation_type":1,"start_name":"jp.co.flect.excel2canvas.format.ExcelDateFormat.JapaneseEra"},{"end_name":"jp.co.flect.excel2canvas.format.ExcelDateFormat.Builder","relation_type":3,"start_name":"jp.co.flect.excel2canvas.format.ExcelDateFormat.JapaneseEra"},{"end_name":"jp.co.flect.excel2canvas.format","relation_type":1,"start_name":"jp.co.flect.excel2canvas.format.ExcelDateFormat.JapaneseYear"},{"end_name":"jp.co.flect.excel2canvas.format.ExcelDateFormat.Builder","relation_type":3,"start_name":"jp.co.flect.excel2canvas.format.ExcelDateFormat.JapaneseYear"},{"end_name":"jp.co.flect.excel2canvas.format","relation_type":1,"start_name":"jp.co.flect.excel2canvas.format.ExcelDateFormat.Month"},{"end_name":"jp.co.flect.excel2canvas.format.ExcelDateFormat.Builder","relation_type":3,"start_name":"jp.co.flect.excel2canvas.format.ExcelDateFormat.Month"},{"end_name":"jp.co.flect.excel2canvas.format","relation_type":1,"start_name":"jp.co.flect.excel2canvas.format.ExcelDateFormat.Day"},{"end_name":"jp.co.flect.excel2canvas.format.ExcelDateFormat.Builder","relation_type":3,"start_name":"jp.co.flect.excel2canvas.format.ExcelDateFormat.Day"},{"end_name":"jp.co.flect.excel2canvas.format","relation_type":1,"start_name":"jp.co.flect.excel2canvas.format.ExcelDateFormat.Week"},{"end_name":"jp.co.flect.excel2canvas.format.ExcelDateFormat.Builder","relation_type":3,"start_name":"jp.co.flect.excel2canvas.format.ExcelDateFormat.Week"},{"end_name":"jp.co.flect.excel2canvas.format","relation_type":1,"start_name":"jp.co.flect.excel2canvas.format.ExcelDateFormat.Hour"},{"end_name":"jp.co.flect.excel2canvas.format.ExcelDateFormat.Builder","relation_type":3,"start_name":"jp.co.flect.excel2canvas.format.ExcelDateFormat.Hour"},{"end_name":"jp.co.flect.excel2canvas.format","relation_type":1,"start_name":"jp.co.flect.excel2canvas.format.ExcelDateFormat.Minute"},{"end_name":"jp.co.flect.excel2canvas.format.ExcelDateFormat.Builder","relation_type":3,"start_name":"jp.co.flect.excel2canvas.format.ExcelDateFormat.Minute"},{"end_name":"jp.co.flect.excel2canvas.format","relation_type":1,"start_name":"jp.co.flect.excel2canvas.format.ExcelDateFormat.Second"},{"end_name":"jp.co.flect.excel2canvas.format.ExcelDateFormat.Builder","relation_type":3,"start_name":"jp.co.flect.excel2canvas.format.ExcelDateFormat.Second"},{"end_name":"jp.co.flect.excel2canvas.format","relation_type":1,"start_name":"jp.co.flect.excel2canvas.format.ExcelDateFormat.SpecialHour"},{"end_name":"jp.co.flect.excel2canvas.format.ExcelDateFormat.Builder","relation_type":3,"start_name":"jp.co.flect.excel2canvas.format.ExcelDateFormat.SpecialHour"},{"end_name":"jp.co.flect.excel2canvas.format","relation_type":1,"start_name":"jp.co.flect.excel2canvas.format.ExcelDateFormat.SpecialMinute"},{"end_name":"jp.co.flect.excel2canvas.format.ExcelDateFormat.SpecialHour","relation_type":2,"start_name":"jp.co.flect.excel2canvas.format.ExcelDateFormat.SpecialMinute"},{"end_name":"jp.co.flect.excel2canvas.format","relation_type":1,"start_name":"jp.co.flect.excel2canvas.format.ExcelDateFormat.SpecialSecond"},{"end_name":"jp.co.flect.excel2canvas.format.ExcelDateFormat.SpecialMinute","relation_type":2,"start_name":"jp.co.flect.excel2canvas.format.ExcelDateFormat.SpecialSecond"},{"end_name":"jp.co.flect.excel2canvas.format","relation_type":1,"start_name":"jp.co.flect.excel2canvas.format.ExcelDateFormat.AmPm"},{"end_name":"jp.co.flect.excel2canvas.format.ExcelDateFormat.Builder","relation_type":3,"start_name":"jp.co.flect.excel2canvas.format.ExcelDateFormat.AmPm"},{"end_name":"jp.co.flect.excel2canvas.format","relation_type":1,"start_name":"jp.co.flect.excel2canvas.format.ExcelDateFormat.MilliSecond"},{"end_name":"jp.co.flect.excel2canvas.format.ExcelDateFormat.Builder","relation_type":3,"start_name":"jp.co.flect.excel2canvas.format.ExcelDateFormat.MilliSecond"},{"end_name":"jp.co.flect.excel2canvas.format","relation_type":1,"start_name":"jp.co.flect.excel2canvas.format.FormatInfo"},{"end_name":"jp.co.flect.excel2canvas.format","relation_type":1,"start_name":"jp.co.flect.excel2canvas.format.FormatInfo.Condition"},{"end_name":"jp.co.flect.excel2canvas.format","relation_type":1,"start_name":"jp.co.flect.excel2canvas.format.FormatInfo.Equal"},{"end_name":"jp.co.flect.excel2canvas.format.FormatInfo.Condition","relation_type":2,"start_name":"jp.co.flect.excel2canvas.format.FormatInfo.Equal"},{"end_name":"jp.co.flect.excel2canvas.format","relation_type":1,"start_name":"jp.co.flect.excel2canvas.format.FormatInfo.NotEqual"},{"end_name":"jp.co.flect.excel2canvas.format.FormatInfo.Condition","relation_type":2,"start_name":"jp.co.flect.excel2canvas.format.FormatInfo.NotEqual"},{"end_name":"jp.co.flect.excel2canvas.format","relation_type":1,"start_name":"jp.co.flect.excel2canvas.format.FormatInfo.LessThan"},{"end_name":"jp.co.flect.excel2canvas.format.FormatInfo.Condition","relation_type":2,"start_name":"jp.co.flect.excel2canvas.format.FormatInfo.LessThan"},{"end_name":"jp.co.flect.excel2canvas.format","relation_type":1,"start_name":"jp.co.flect.excel2canvas.format.FormatInfo.LessEqual"},{"end_name":"jp.co.flect.excel2canvas.format.FormatInfo.Condition","relation_type":2,"start_name":"jp.co.flect.excel2canvas.format.FormatInfo.LessEqual"},{"end_name":"jp.co.flect.excel2canvas.format","relation_type":1,"start_name":"jp.co.flect.excel2canvas.format.FormatInfo.GreaterThan"},{"end_name":"jp.co.flect.excel2canvas.format.FormatInfo.Condition","relation_type":2,"start_name":"jp.co.flect.excel2canvas.format.FormatInfo.GreaterThan"},{"end_name":"jp.co.flect.excel2canvas.format","relation_type":1,"start_name":"jp.co.flect.excel2canvas.format.FormatInfo.GreaterEqual"},{"end_name":"jp.co.flect.excel2canvas.format.FormatInfo.Condition","relation_type":2,"start_name":"jp.co.flect.excel2canvas.format.FormatInfo.GreaterEqual"},{"end_name":"jp.co.flect.excel2canvas.format","relation_type":1,"start_name":"jp.co.flect.excel2canvas.format.FormatHolder"},{"end_name":"jp.co.flect.excel2canvas.functions","relation_type":1,"start_name":"jp.co.flect.excel2canvas.functions.Weekday"},{"end_name":"jp.co.flect.excel2canvas.functions","relation_type":1,"start_name":"jp.co.flect.excel2canvas.functions.FunctionManager"},{"end_name":"jp.co.flect.excel2canvas","relation_type":1,"start_name":"jp.co.flect.excel2canvas.ExcelColor"},{"end_name":"jp.co.flect.excel2canvas","relation_type":1,"start_name":"jp.co.flect.excel2canvas.CellValueHelper"},{"end_name":"jp.co.flect.excel2canvas","relation_type":1,"start_name":"jp.co.flect.excel2canvas.CellValueHelper.ExceptionHandler"},{"end_name":"jp.co.flect.excel2canvas","relation_type":1,"start_name":"jp.co.flect.excel2canvas.ImageWriter"},{"end_name":"jp.co.flect.excel2canvas","relation_type":1,"start_name":"jp.co.flect.excel2canvas.DataFormatterEx"},{"end_name":"jp.co.flect.excel2canvas","relation_type":1,"start_name":"jp.co.flect.excel2canvas.NamedCellInfo"},{"end_name":"jp.co.flect.excel2canvas","relation_type":1,"start_name":"jp.co.flect.excel2canvas.FormattedValue"}]